json2dynamo/__init__.py
json2dynamo/app.py
json2dynamo/util.py
json2dynamo-0.2.2.dist-info/LICENSE
json2dynamo-0.2.2.dist-info/METADATA
json2dynamo-0.2.2.dist-info/WHEEL
json2dynamo-0.2.2.dist-info/entry_points.txt
json2dynamo-0.2.2.dist-info/top_level.txt
json2dynamo-0.2.2.dist-info/RECORD
