Metadata-Version: 2.1
Name: json2dynamo
Version: 0.2.2
Summary: UNKNOWN
Home-page: https://github.com/allankp/json2dynamo
Author: Allan Kilpatrick
Author-email: allanklp@gmail.com
License: UNKNOWN
Platform: UNKNOWN
Requires-Dist: dynamodb-json (==1.3)
Requires-Dist: Click (==7.0)
